setup.cfg
setup.py
src/fixt/__init__.py
src/fixt/_cleanups.py
src/fixt/_fixt.py
src/fixt/_monkeypatch.py
src/fixt/_version.py
src/fixt.egg-info/PKG-INFO
src/fixt.egg-info/SOURCES.txt
src/fixt.egg-info/dependency_links.txt
src/fixt.egg-info/top_level.txt
src/fixt.egg-info/zip-safe