Metadata-Version: 1.1
Name: fixt
Version: 0.1.0
Summary: Make objects for use in tests, automatically making dependencies
Home-page: https://github.com/jlee_made/fixt
Author: John Lee
Author-email: UNKNOWN
License: MIT
Platform: any
Classifier: Development Status :: 4 - Beta
Classifier: Intended Audience :: Developers
Classifier: License :: OSI Approved :: MIT License
Classifier: Operating System :: POSIX
Classifier: Programming Language :: Python :: 3
